color_utils/__init__.py
color_utils/qcolor.py
tintelligence_color_utils/__init__.py
tintelligence_color_utils/conversion.py
tintelligence_color_utils/families.py
tintelligence_color_utils/family.py
tintelligence_color_utils/qcolor.py
tintelligence_color_utils/shades.py
tintelligence_color_utils/sorting.py
tintelligence_color_utils-0.1.10.dist-info/METADATA
tintelligence_color_utils-0.1.10.dist-info/WHEEL
tintelligence_color_utils-0.1.10.dist-info/licenses/LICENSE
tintelligence_color_utils-0.1.10.dist-info/RECORD
