Metadata-Version: 2.4
Name: tintelligence-color-utils
Version: 0.1.10
Summary: Utility functions for working with colors (conversion, manipulation, validation).
Project-URL: Homepage, https://github.com/Tintelligence-App/color-utils
Project-URL: Repository, https://github.com/Tintelligence-App/color-utils
Project-URL: Issues, https://github.com/Tintelligence-App/color-utils/issues
Author: tintelligence
License: MIT License
License-File: LICENSE
Keywords: color,color-conversion,colors,hsl,lab,lch,rgb
Classifier: Intended Audience :: Developers
Classifier: License :: OSI Approved :: MIT License
Classifier: Operating System :: OS Independent
Classifier: Programming Language :: Python :: 3
Classifier: Programming Language :: Python :: 3 :: Only
Classifier: Programming Language :: Python :: 3.9
Classifier: Programming Language :: Python :: 3.10
Classifier: Programming Language :: Python :: 3.11
Classifier: Programming Language :: Python :: 3.12
Classifier: Typing :: Typed
Requires-Python: >=3.9
Provides-Extra: dev
Requires-Dist: build>=1.2.1; extra == 'dev'
Requires-Dist: pytest>=7.0; extra == 'dev'
Provides-Extra: qt-pyqt6
Requires-Dist: pyqt6>=6.5; extra == 'qt-pyqt6'
Provides-Extra: qt-pyside6
Requires-Dist: pyside6>=6.5; extra == 'qt-pyside6'
